<?xml version="1.0" encoding="utf-8" ?>
<dwsync>
<file name="gobutton.jpg" server="ftp.dialself.org" local="129641994600000000" remote="129641994600000000" Dst="-1" />
<file name="search_01.jpg" server="ftp.dialself.org" local="129641344105008455" remote="129641959200000000" Dst="-1" />
<file name="search_03.jpg" server="ftp.dialself.org" local="129641995200000000" remote="129641995200000000" Dst="-1" />
<file name="search_05.jpg" server="ftp.dialself.org" local="129641995200000000" remote="129641995200000000" Dst="-1" />
<file name="search_06.jpg" server="ftp.dialself.org" local="129641995200000000" remote="129641995200000000" Dst="-1" />
<file name="search_08.jpg" server="ftp.dialself.org" local="129641995200000000" remote="129641995200000000" Dst="-1" />
<file name="search_07.jpg" server="ftp.dialself.org" local="129641995200000000" remote="129641995200000000" Dst="-1" />
<file name="search_09.jpg" server="ftp.dialself.org" local="129641995200000000" remote="129641995200000000" Dst="-1" />
<file name="search_10.jpg" server="ftp.dialself.org" local="129641995200000000" remote="129641995200000000" Dst="-1" />
<file name="search_11.jpg" server="ftp.dialself.org" local="129641995200000000" remote="129641995200000000" Dst="-1" />
<file name="search_12.jpg" server="ftp.dialself.org" local="129641995200000000" remote="129641995200000000" Dst="-1" />
<file name="search_13.jpg" server="ftp.dialself.org" local="129641995200000000" remote="129641995200000000" Dst="-1" />
<file name="search.jpg" server="ftp.dialself.org" local="129641995200000000" remote="129641995200000000" Dst="-1" />
<file name="search_02.jpg" server="ftp.dialself.org" local="129641995200000000" remote="129641995200000000" Dst="-1" />
<file name="search_04.jpg" server="ftp.dialself.org" local="129641995200000000" remote="129641995200000000" Dst="-1" />
<file name="bof10kcoverphoto.jpg" server="ftp.dialself.org" local="130753435200000000" remote="130753330800000000" Dst="2" />
</dwsync>